{
	"refreshDateTime": "2025-11-24 16:05:57",
	"Site": [
		{
			"Code": "973",
			"SiteName": "Loch Con",
			"SiteDesignation": "SSSI",
			"LocalAuthority": "Perth and Kinross",
			"SNHArea": "National Operations Central Highland",
			"ProtectedOverlays": {
				"Overlay": [
					{
						"Type": "VICE_COUNTIES",
						"Ref": "Mid Perth",
						"Prime": "P",
						"Overlap": 49.27,
						"Percentage": 100
					},
					{
						"Type": "DEER_MANAGEMENT_GROUP",
						"Ref": "East Loch Ericht",
						"Prime": "P",
						"Overlap": 49.27,
						"Percentage": 100
					},
					{
						"Type": "SEPA_SUB_BASIN_DISTRICTS",
						"Ref": "Tay",
						"Prime": "P",
						"Overlap": 49.27,
						"Percentage": 100
					}
				]
			},
			"SiteFeature": [
				{
					"Id": "11437",
					"Name": "Vascular plant assemblage",
					"ActionPlanFeature": "N",
					"WaterFeature": "N",
					"Category": "Vascular plants",
					"Subcategory": "Vascular plants",
					"SummaryCondition": "Favourable",
					"LatestAssessedCondition": "Favourable Maintained",
					"LatestAssessedVisitDate": "2010-08-06",
					"LatestAssessedSCMcycle": "2",
					"FeatureType": "Species",
					"Pressures": {
						"Pressure": []
					},
					"HistoryDetails": {
						"Year": [
							{
								"year": "2023",
								"AnnualSummaryCondition": "Favourable"
							},
							{
								"year": "2021",
								"AnnualSummaryCondition": "Favourable"
							},
							{
								"year": "2020",
								"AnnualSummaryCondition": "Favourable"
							},
							{
								"year": "2019",
								"AnnualSummaryCondition": "Favourable"
							},
							{
								"year": "2018",
								"AnnualSummaryCondition": "Favourable"
							},
							{
								"year": "2017",
								"AnnualSummaryCondition": "Favourable"
							},
							{
								"year": "2016",
								"AnnualSummaryCondition": "Favourable"
							},
							{
								"year": "2015",
								"AnnualSummaryCondition": "Favourable"
							},
							{
								"year": "2014",
								"AnnualSummaryCondition": "Favourable"
							},
							{
								"year": "2013",
								"AnnualSummaryCondition": "Favourable"
							},
							{
								"year": "2012",
								"AnnualSummaryCondition": "Favourable"
							},
							{
								"year": "2011",
								"AnnualSummaryCondition": "Favourable"
							},
							{
								"year": "2010",
								"AnnualSummaryCondition": "Not Assessed"
							}
						]
					}
				},
				{
					"Id": "11438",
					"Name": "Breeding bird assemblage",
					"ActionPlanFeature": "N",
					"WaterFeature": "Y",
					"Category": "Birds",
					"Subcategory": "Birds - assemblages of breeding birds",
					"SummaryCondition": "Favourable",
					"LatestAssessedCondition": "Favourable Maintained",
					"LatestAssessedVisitDate": "2013-07-06",
					"LatestAssessedSCMcycle": "3",
					"FeatureType": "Species",
					"Pressures": {
						"Pressure": [
							{
								"Description": "Recreation/disturbance",
								"PressureRecordedAs": "Recreation/disturbance"
							}
						]
					},
					"HistoryDetails": {
						"Year": [
							{
								"year": "2023",
								"AnnualSummaryCondition": "Favourable"
							},
							{
								"year": "2021",
								"AnnualSummaryCondition": "Favourable"
							},
							{
								"year": "2020",
								"AnnualSummaryCondition": "Favourable"
							},
							{
								"year": "2019",
								"AnnualSummaryCondition": "Favourable"
							},
							{
								"year": "2018",
								"AnnualSummaryCondition": "Favourable"
							},
							{
								"year": "2017",
								"AnnualSummaryCondition": "Favourable"
							},
							{
								"year": "2016",
								"AnnualSummaryCondition": "Favourable"
							},
							{
								"year": "2015",
								"AnnualSummaryCondition": "Favourable"
							},
							{
								"year": "2014",
								"AnnualSummaryCondition": "Favourable"
							},
							{
								"year": "2013",
								"AnnualSummaryCondition": "Favourable"
							},
							{
								"year": "2012",
								"AnnualSummaryCondition": "Favourable"
							},
							{
								"year": "2011",
								"AnnualSummaryCondition": "Favourable"
							},
							{
								"year": "2010",
								"AnnualSummaryCondition": "Favourable"
							}
						]
					}
				}
			]
		}
	]
}