{
	"refreshDateTime": "2026-02-12 16:08:47",
	"Site": [
		{
			"Code": "1631",
			"SiteName": "Whitehills to Melrose Coast",
			"SiteDesignation": "SSSI",
			"LocalAuthority": "Aberdeenshire",
			"SNHArea": "National Operations North",
			"ProtectedOverlays": {
				"Overlay": [
					{
						"Type": "VICE_COUNTIES",
						"Ref": "Banff",
						"Prime": "P",
						"Overlap": 90.29,
						"Percentage": 100
					},
					{
						"Type": "SCOTTISH_MARINE_REGIONS",
						"Ref": "Moray Firth",
						"Prime": "P",
						"Overlap": 72.83,
						"Percentage": 81
					},
					{
						"Type": "SEPA_SUB_BASIN_DISTRICTS",
						"Ref": "North East Scotland",
						"Prime": "P",
						"Overlap": 90.29,
						"Percentage": 100
					}
				]
			},
			"SiteFeature": [
				{
					"Id": "12959",
					"Name": "Dalradian",
					"ActionPlanFeature": "N",
					"WaterFeature": "Y",
					"Category": "Earth sciences",
					"Subcategory": "Structural and metamorphic geology",
					"SummaryCondition": "Favourable",
					"LatestAssessedCondition": "Favourable Maintained",
					"LatestAssessedVisitDate": "2006-11-15",
					"LatestAssessedSCMcycle": "2",
					"FeatureType": "Earth Sciences",
					"Pressures": {
						"Pressure": [
							{
								"Description": "Dumping/ storage of materials",
								"PressureRecordedAs": "Dumping/spreading/storage of materials"
							},
							{
								"Description": "Flood defence/coastal defence works",
								"PressureRecordedAs": "Flood defence/coastal defence works"
							}
						]
					},
					"HistoryDetails": {
						"Year": [
							{
								"year": "2023",
								"AnnualSummaryCondition": "Favourable"
							},
							{
								"year": "2021",
								"AnnualSummaryCondition": "Favourable"
							},
							{
								"year": "2020",
								"AnnualSummaryCondition": "Favourable"
							},
							{
								"year": "2019",
								"AnnualSummaryCondition": "Favourable"
							},
							{
								"year": "2018",
								"AnnualSummaryCondition": "Favourable"
							},
							{
								"year": "2017",
								"AnnualSummaryCondition": "Favourable"
							},
							{
								"year": "2016",
								"AnnualSummaryCondition": "Favourable"
							},
							{
								"year": "2015",
								"AnnualSummaryCondition": "Favourable"
							},
							{
								"year": "2014",
								"AnnualSummaryCondition": "Favourable"
							},
							{
								"year": "2013",
								"AnnualSummaryCondition": "Favourable"
							},
							{
								"year": "2012",
								"AnnualSummaryCondition": "Favourable"
							},
							{
								"year": "2011",
								"AnnualSummaryCondition": "Favourable"
							},
							{
								"year": "2010",
								"AnnualSummaryCondition": "Favourable"
							}
						]
					}
				}
			]
		}
	]
}