{
	"refreshDateTime": "2023-02-23 04:17:46",
	"Site": [
		{
			"Code": "186",
			"SiteName": "Ben Lomond",
			"SiteDesignation": "SSSI",
			"LocalAuthority": "Stirling",
			"SNHArea": "National Operations South",
			"NationalPark": "Loch Lomond and The Trossachs",
			"ProtectedOverlays": {
				"Overlay": [
					{
						"Type": "VICE_COUNTIES",
						"Ref": "Stirling",
						"Prime": "P",
						"Overlap": 2374.17,
						"Percentage": 100
					},
					{
						"Type": "SEPA_SUB_BASIN_DISTRICTS",
						"Ref": "Forth",
						"Prime": "S",
						"Overlap": 1084.56,
						"Percentage": 46
					},
					{
						"Type": "SEPA_SUB_BASIN_DISTRICTS",
						"Ref": "Clyde",
						"Prime": "P",
						"Overlap": 1289.62,
						"Percentage": 54
					}
				]
			},
			"SiteFeature": [
				{
					"Id": "9828",
					"Name": "Subalpine dry heath",
					"ActionPlanFeature": "Y",
					"WaterFeature": "N",
					"Category": "Upland habitat",
					"Subcategory": "Dwarf shrub heath (Upland)",
					"SummaryCondition": "Favourable",
					"LatestAssessedCondition": "Unfavourable Recovering",
					"LatestAssessedVisitDate": "2014-09-08",
					"LatestAssessedSCMcycle": "3",
					"FeatureType": "Habitats",
					"Pressures": {
						"Pressure": [
							{
								"Description": "Invasive species",
								"PressureRecordedAs": "Presence/changing extent invasive species - NON NATIVE",
								"keywords": "Sitka Spruce"
							}
						]
					},
					"HistoryDetails": {
						"Year": [
							{
								"year": "2021",
								"AnnualSummaryCondition": "Favourable"
							},
							{
								"year": "2020",
								"AnnualSummaryCondition": "Favourable"
							},
							{
								"year": "2019",
								"AnnualSummaryCondition": "Favourable"
							},
							{
								"year": "2018",
								"AnnualSummaryCondition": "Favourable"
							},
							{
								"year": "2017",
								"AnnualSummaryCondition": "Recovering"
							},
							{
								"year": "2016",
								"AnnualSummaryCondition": "Recovering"
							},
							{
								"year": "2015",
								"AnnualSummaryCondition": "Unfavourable"
							},
							{
								"year": "2014",
								"AnnualSummaryCondition": "Unfavourable"
							},
							{
								"year": "2013",
								"AnnualSummaryCondition": "Unfavourable"
							},
							{
								"year": "2012",
								"AnnualSummaryCondition": "Unfavourable"
							},
							{
								"year": "2011",
								"AnnualSummaryCondition": "Unfavourable"
							},
							{
								"year": "2010",
								"AnnualSummaryCondition": "Recovering"
							}
						]
					}
				},
				{
					"Id": "9831",
					"Name": "Vascular plant assemblage",
					"ActionPlanFeature": "N",
					"WaterFeature": "N",
					"Category": "Vascular plants",
					"Subcategory": "Vascular plants",
					"SummaryCondition": "Recovering",
					"LatestAssessedCondition": "Unfavourable Declining",
					"LatestAssessedVisitDate": "2005-08-22",
					"LatestAssessedSCMcycle": "2",
					"FeatureType": "Species",
					"Pressures": {
						"Pressure": [
							{
								"Description": "Over grazing",
								"PressureRecordedAs": "Grazing - over",
								"keywords": "Sheep"
							}
						]
					},
					"HistoryDetails": {
						"Year": [
							{
								"year": "2021",
								"AnnualSummaryCondition": "Recovering"
							},
							{
								"year": "2020",
								"AnnualSummaryCondition": "Recovering"
							},
							{
								"year": "2019",
								"AnnualSummaryCondition": "Recovering"
							},
							{
								"year": "2018",
								"AnnualSummaryCondition": "Recovering"
							},
							{
								"year": "2017",
								"AnnualSummaryCondition": "Recovering"
							},
							{
								"year": "2016",
								"AnnualSummaryCondition": "Recovering"
							},
							{
								"year": "2015",
								"AnnualSummaryCondition": "Unfavourable"
							},
							{
								"year": "2014",
								"AnnualSummaryCondition": "Unfavourable"
							},
							{
								"year": "2013",
								"AnnualSummaryCondition": "Unfavourable"
							},
							{
								"year": "2012",
								"AnnualSummaryCondition": "Unfavourable"
							},
							{
								"year": "2011",
								"AnnualSummaryCondition": "Not Assessed"
							},
							{
								"year": "2010",
								"AnnualSummaryCondition": "Recovering"
							}
						]
					}
				},
				{
					"Id": "9833",
					"Name": "Upland assemblage",
					"ActionPlanFeature": "N",
					"WaterFeature": "N",
					"Category": "Upland habitat",
					"Subcategory": "Mosaic",
					"SummaryCondition": "Unfavourable",
					"LatestAssessedCondition": "Unfavourable No change",
					"LatestAssessedVisitDate": "2020-09-21",
					"LatestAssessedSCMcycle": "4",
					"FeatureType": "Habitats",
					"Pressures": {
						"Pressure": [
							{
								"Description": "Over grazing",
								"PressureRecordedAs": "Grazing - over",
								"keywords": "Sheep"
							}
						]
					},
					"HistoryDetails": {
						"Year": [
							{
								"year": "2021",
								"AnnualSummaryCondition": "Recovering"
							},
							{
								"year": "2020",
								"AnnualSummaryCondition": "Recovering"
							},
							{
								"year": "2019",
								"AnnualSummaryCondition": "Recovering"
							},
							{
								"year": "2018",
								"AnnualSummaryCondition": "Unfavourable"
							},
							{
								"year": "2017",
								"AnnualSummaryCondition": "Favourable"
							},
							{
								"year": "2016",
								"AnnualSummaryCondition": "Favourable"
							},
							{
								"year": "2015",
								"AnnualSummaryCondition": "Favourable"
							},
							{
								"year": "2014",
								"AnnualSummaryCondition": "Favourable"
							},
							{
								"year": "2013",
								"AnnualSummaryCondition": "Favourable"
							},
							{
								"year": "2012",
								"AnnualSummaryCondition": "Favourable"
							},
							{
								"year": "2011",
								"AnnualSummaryCondition": "Favourable"
							},
							{
								"year": "2010",
								"AnnualSummaryCondition": "Favourable"
							}
						]
					}
				},
				{
					"Id": "14940",
					"Name": "Snowbed",
					"ActionPlanFeature": "N",
					"WaterFeature": "N",
					"Category": "Upland habitat",
					"Subcategory": "Montane habitats",
					"SummaryCondition": "Unfavourable",
					"LatestAssessedCondition": "Unfavourable Declining",
					"LatestAssessedVisitDate": "2004-11-18",
					"LatestAssessedSCMcycle": "1",
					"FeatureType": "Habitats",
					"Pressures": {
						"Pressure": [
							{
								"Description": "Over grazing",
								"PressureRecordedAs": "Grazing - over",
								"keywords": "Sheep"
							}
						]
					},
					"HistoryDetails": {
						"Year": [
							{
								"year": "2021",
								"AnnualSummaryCondition": "Unfavourable"
							},
							{
								"year": "2020",
								"AnnualSummaryCondition": "Unfavourable"
							},
							{
								"year": "2019",
								"AnnualSummaryCondition": "Unfavourable"
							},
							{
								"year": "2018",
								"AnnualSummaryCondition": "Unfavourable"
							},
							{
								"year": "2017",
								"AnnualSummaryCondition": "Unfavourable"
							},
							{
								"year": "2016",
								"AnnualSummaryCondition": "Unfavourable"
							},
							{
								"year": "2015",
								"AnnualSummaryCondition": "Unfavourable"
							},
							{
								"year": "2014",
								"AnnualSummaryCondition": "Unfavourable"
							},
							{
								"year": "2013",
								"AnnualSummaryCondition": "Unfavourable"
							},
							{
								"year": "2012",
								"AnnualSummaryCondition": "Unfavourable"
							},
							{
								"year": "2011",
								"AnnualSummaryCondition": "Unfavourable"
							},
							{
								"year": "2010",
								"AnnualSummaryCondition": "Recovering"
							}
						]
					}
				},
				{
					"Id": "15000",
					"Name": "Invertebrate assemblage",
					"ActionPlanFeature": "N",
					"WaterFeature": "N",
					"Category": "Invertebrates",
					"Subcategory": "Other invertebrates",
					"SummaryCondition": "Favourable",
					"LatestAssessedCondition": "Favourable Maintained",
					"LatestAssessedVisitDate": "2013-07-09",
					"LatestAssessedSCMcycle": "3",
					"FeatureType": "Species",
					"Pressures": {
						"Pressure": []
					},
					"HistoryDetails": {
						"Year": [
							{
								"year": "2021",
								"AnnualSummaryCondition": "Favourable"
							},
							{
								"year": "2020",
								"AnnualSummaryCondition": "Favourable"
							},
							{
								"year": "2019",
								"AnnualSummaryCondition": "Favourable"
							},
							{
								"year": "2018",
								"AnnualSummaryCondition": "Favourable"
							},
							{
								"year": "2017",
								"AnnualSummaryCondition": "Favourable"
							},
							{
								"year": "2016",
								"AnnualSummaryCondition": "Favourable"
							},
							{
								"year": "2015",
								"AnnualSummaryCondition": "Favourable"
							},
							{
								"year": "2014",
								"AnnualSummaryCondition": "Favourable"
							},
							{
								"year": "2013",
								"AnnualSummaryCondition": "Favourable"
							},
							{
								"year": "2012",
								"AnnualSummaryCondition": "Favourable"
							},
							{
								"year": "2011",
								"AnnualSummaryCondition": "Favourable"
							},
							{
								"year": "2010",
								"AnnualSummaryCondition": "Favourable"
							}
						]
					}
				}
			]
		}
	]
}