{
	"refreshDateTime": "2025-10-20 16:04:56",
	"Site": [
		{
			"Code": "1355",
			"SiteName": "Riskinhope",
			"SiteDesignation": "SSSI",
			"LocalAuthority": "Scottish Borders",
			"SNHArea": "National Operations South",
			"ProtectedOverlays": {
				"Overlay": [
					{
						"Type": "VICE_COUNTIES",
						"Ref": "Selkirk",
						"Prime": "P",
						"Overlap": 8.31,
						"Percentage": 100
					},
					{
						"Type": "DEER_MANAGEMENT_GROUP",
						"Ref": "Eskdalemuir",
						"Prime": "P",
						"Overlap": 8.31,
						"Percentage": 100
					},
					{
						"Type": "SEPA_SUB_BASIN_DISTRICTS",
						"Ref": "Tweed",
						"Prime": "P",
						"Overlap": 8.31,
						"Percentage": 100
					}
				]
			},
			"SiteFeature": [
				{
					"Id": "12292",
					"Name": "Flood-plain fen",
					"ActionPlanFeature": "N",
					"WaterFeature": "Y",
					"Category": "Wetlands",
					"Subcategory": "Fen, marsh and swamp (Wetland)",
					"SummaryCondition": "Favourable",
					"LatestAssessedCondition": "Favourable Maintained",
					"LatestAssessedVisitDate": "2003-08-19",
					"LatestAssessedSCMcycle": "1",
					"FeatureType": "Habitats",
					"Pressures": {
						"Pressure": [
							{
								"Description": "No proactive management",
								"PressureRecordedAs": "Lack of remedial management"
							}
						]
					},
					"HistoryDetails": {
						"Year": [
							{
								"year": "2023",
								"AnnualSummaryCondition": "Favourable"
							},
							{
								"year": "2021",
								"AnnualSummaryCondition": "Favourable"
							},
							{
								"year": "2020",
								"AnnualSummaryCondition": "Favourable"
							},
							{
								"year": "2019",
								"AnnualSummaryCondition": "Favourable"
							},
							{
								"year": "2018",
								"AnnualSummaryCondition": "Favourable"
							},
							{
								"year": "2017",
								"AnnualSummaryCondition": "Favourable"
							},
							{
								"year": "2016",
								"AnnualSummaryCondition": "Favourable"
							},
							{
								"year": "2015",
								"AnnualSummaryCondition": "Favourable"
							},
							{
								"year": "2014",
								"AnnualSummaryCondition": "Favourable"
							},
							{
								"year": "2013",
								"AnnualSummaryCondition": "Favourable"
							},
							{
								"year": "2012",
								"AnnualSummaryCondition": "Favourable"
							},
							{
								"year": "2011",
								"AnnualSummaryCondition": "Favourable"
							},
							{
								"year": "2010",
								"AnnualSummaryCondition": "Favourable"
							}
						]
					}
				}
			]
		}
	]
}