{
	"refreshDateTime": "2024-12-21 15:55:13",
	"Site": [
		{
			"Code": "1648",
			"SiteName": "Woodhead Moss",
			"SiteDesignation": "SSSI",
			"LocalAuthority": "Scottish Borders",
			"SNHArea": "National Operations South",
			"ProtectedOverlays": {
				"Overlay": [
					{
						"Type": "VICE_COUNTIES",
						"Ref": "Roxburgh",
						"Prime": "P",
						"Overlap": 14.32,
						"Percentage": 100
					},
					{
						"Type": "SEPA_SUB_BASIN_DISTRICTS",
						"Ref": "Tweed",
						"Prime": "P",
						"Overlap": 14.32,
						"Percentage": 100
					}
				]
			},
			"SiteFeature": [
				{
					"Id": "13007",
					"Name": "Wet woodland",
					"ActionPlanFeature": "N",
					"WaterFeature": "Y",
					"Category": "Woodland",
					"Subcategory": "Broad-leaved, mixed and yew woodland",
					"SummaryCondition": "Favourable",
					"LatestAssessedCondition": "Favourable Maintained",
					"LatestAssessedVisitDate": "2009-06-09",
					"LatestAssessedSCMcycle": "2",
					"FeatureType": "Habitats",
					"Pressures": {
						"Pressure": [
							{
								"Description": "Invasive species",
								"PressureRecordedAs": "Presence/changing extent invasive species - NATIVE",
								"keywords": "Other (add species to the pressure comment)"
							}
						]
					},
					"HistoryDetails": {
						"Year": [
							{
								"year": "2023",
								"AnnualSummaryCondition": "Favourable"
							},
							{
								"year": "2021",
								"AnnualSummaryCondition": "Favourable"
							},
							{
								"year": "2020",
								"AnnualSummaryCondition": "Favourable"
							},
							{
								"year": "2019",
								"AnnualSummaryCondition": "Favourable"
							},
							{
								"year": "2018",
								"AnnualSummaryCondition": "Favourable"
							},
							{
								"year": "2017",
								"AnnualSummaryCondition": "Favourable"
							},
							{
								"year": "2016",
								"AnnualSummaryCondition": "Favourable"
							},
							{
								"year": "2015",
								"AnnualSummaryCondition": "Favourable"
							},
							{
								"year": "2014",
								"AnnualSummaryCondition": "Favourable"
							},
							{
								"year": "2013",
								"AnnualSummaryCondition": "Favourable"
							},
							{
								"year": "2012",
								"AnnualSummaryCondition": "Favourable"
							},
							{
								"year": "2011",
								"AnnualSummaryCondition": "Favourable"
							},
							{
								"year": "2010",
								"AnnualSummaryCondition": "Favourable"
							}
						]
					}
				},
				{
					"Id": "13008",
					"Name": "Basin fen",
					"ActionPlanFeature": "N",
					"WaterFeature": "Y",
					"Category": "Wetlands",
					"Subcategory": "Fen, marsh and swamp (Wetland)",
					"SummaryCondition": "Unfavourable",
					"LatestAssessedCondition": "Unfavourable Declining",
					"LatestAssessedVisitDate": "2014-07-29",
					"LatestAssessedSCMcycle": "3",
					"FeatureType": "Habitats",
					"Pressures": {
						"Pressure": [
							{
								"Description": "Invasive species",
								"PressureRecordedAs": "Presence/changing extent invasive species - NON NATIVE"
							},
							{
								"Description": "Water management",
								"PressureRecordedAs": "Water management"
							}
						]
					},
					"HistoryDetails": {
						"Year": [
							{
								"year": "2023",
								"AnnualSummaryCondition": "Unfavourable"
							},
							{
								"year": "2021",
								"AnnualSummaryCondition": "Unfavourable"
							},
							{
								"year": "2020",
								"AnnualSummaryCondition": "Unfavourable"
							},
							{
								"year": "2019",
								"AnnualSummaryCondition": "Unfavourable"
							},
							{
								"year": "2018",
								"AnnualSummaryCondition": "Unfavourable"
							},
							{
								"year": "2017",
								"AnnualSummaryCondition": "Unfavourable"
							},
							{
								"year": "2016",
								"AnnualSummaryCondition": "Unfavourable"
							},
							{
								"year": "2015",
								"AnnualSummaryCondition": "Unfavourable"
							},
							{
								"year": "2014",
								"AnnualSummaryCondition": "Favourable"
							},
							{
								"year": "2013",
								"AnnualSummaryCondition": "Favourable"
							},
							{
								"year": "2012",
								"AnnualSummaryCondition": "Favourable"
							},
							{
								"year": "2011",
								"AnnualSummaryCondition": "Favourable"
							},
							{
								"year": "2010",
								"AnnualSummaryCondition": "Favourable"
							}
						]
					}
				}
			]
		}
	]
}