{
	"refreshDateTime": "2025-10-18 16:04:52",
	"Site": [
		{
			"Code": "558",
			"SiteName": "Dunaskin Glen",
			"SiteDesignation": "SSSI",
			"LocalAuthority": "East Ayrshire",
			"SNHArea": "National Operations West Central",
			"ProtectedOverlays": {
				"Overlay": [
					{
						"Type": "VICE_COUNTIES",
						"Ref": "Ayrshire",
						"Prime": "P",
						"Overlap": 26.09,
						"Percentage": 100
					},
					{
						"Type": "DEER_MANAGEMENT_GROUP",
						"Ref": "West Dumfries and Galloway",
						"Prime": "P",
						"Overlap": 26.09,
						"Percentage": 100
					},
					{
						"Type": "SEPA_SUB_BASIN_DISTRICTS",
						"Ref": "Clyde",
						"Prime": "P",
						"Overlap": 26.09,
						"Percentage": 100
					}
				]
			},
			"SiteFeature": [
				{
					"Id": "10577",
					"Name": "Upper Carboniferous [Namurian (part) - Westphalian]",
					"ActionPlanFeature": "N",
					"WaterFeature": "Y",
					"Category": "Earth sciences",
					"Subcategory": "Stratigraphy",
					"SummaryCondition": "Favourable",
					"LatestAssessedCondition": "Favourable Maintained",
					"LatestAssessedVisitDate": "2007-02-05",
					"LatestAssessedSCMcycle": "2",
					"FeatureType": "Earth Sciences",
					"Pressures": {
						"Pressure": []
					},
					"HistoryDetails": {
						"Year": [
							{
								"year": "2023",
								"AnnualSummaryCondition": "Favourable"
							},
							{
								"year": "2021",
								"AnnualSummaryCondition": "Favourable"
							},
							{
								"year": "2020",
								"AnnualSummaryCondition": "Favourable"
							},
							{
								"year": "2019",
								"AnnualSummaryCondition": "Favourable"
							},
							{
								"year": "2018",
								"AnnualSummaryCondition": "Favourable"
							},
							{
								"year": "2017",
								"AnnualSummaryCondition": "Favourable"
							},
							{
								"year": "2016",
								"AnnualSummaryCondition": "Favourable"
							},
							{
								"year": "2015",
								"AnnualSummaryCondition": "Favourable"
							},
							{
								"year": "2014",
								"AnnualSummaryCondition": "Favourable"
							},
							{
								"year": "2013",
								"AnnualSummaryCondition": "Favourable"
							},
							{
								"year": "2012",
								"AnnualSummaryCondition": "Favourable"
							},
							{
								"year": "2011",
								"AnnualSummaryCondition": "Favourable"
							},
							{
								"year": "2010",
								"AnnualSummaryCondition": "Favourable"
							}
						]
					}
				},
				{
					"Id": "16371",
					"Name": "Palaeozoic Palaeobotany",
					"ActionPlanFeature": "N",
					"WaterFeature": "N",
					"Category": "Earth sciences",
					"Subcategory": "Palaeontology",
					"SummaryCondition": "Favourable",
					"LatestAssessedCondition": "Favourable Maintained",
					"LatestAssessedVisitDate": "2015-01-29",
					"LatestAssessedSCMcycle": "3",
					"FeatureType": "Earth Sciences",
					"Pressures": {
						"Pressure": []
					},
					"HistoryDetails": {
						"Year": [
							{
								"year": "2023",
								"AnnualSummaryCondition": "Favourable"
							},
							{
								"year": "2021",
								"AnnualSummaryCondition": "Favourable"
							},
							{
								"year": "2020",
								"AnnualSummaryCondition": "Favourable"
							},
							{
								"year": "2019",
								"AnnualSummaryCondition": "Favourable"
							},
							{
								"year": "2018",
								"AnnualSummaryCondition": "Favourable"
							},
							{
								"year": "2017",
								"AnnualSummaryCondition": "Favourable"
							},
							{
								"year": "2016",
								"AnnualSummaryCondition": "Favourable"
							},
							{
								"year": "2015",
								"AnnualSummaryCondition": "Favourable"
							},
							{
								"year": "2014",
								"AnnualSummaryCondition": "Favourable"
							},
							{
								"year": "2013",
								"AnnualSummaryCondition": "Favourable"
							},
							{
								"year": "2012",
								"AnnualSummaryCondition": "Favourable"
							},
							{
								"year": "2011",
								"AnnualSummaryCondition": "Not Assessed"
							},
							{
								"year": "2010",
								"AnnualSummaryCondition": "Not Assessed"
							}
						]
					}
				}
			]
		}
	]
}