{
	"refreshDateTime": "2024-06-30 15:49:09",
	"Site": [
		{
			"Code": "8336",
			"SiteName": "Mull of Galloway",
			"SiteDesignation": "SAC",
			"LocalAuthority": "Dumfries and Galloway",
			"SNHArea": "National Operations South",
			"ProtectedOverlays": {
				"Overlay": [
					{
						"Type": "VICE_COUNTIES",
						"Ref": "Wigtownshire",
						"Prime": "P",
						"Overlap": 137.14,
						"Percentage": 100
					},
					{
						"Type": "SCOTTISH_MARINE_REGIONS",
						"Ref": "Solway",
						"Prime": "P",
						"Overlap": 30.72,
						"Percentage": 22
					},
					{
						"Type": "DEER_MANAGEMENT_GROUP",
						"Ref": "West Dumfries and Galloway",
						"Prime": "P",
						"Overlap": 117.53,
						"Percentage": 86
					},
					{
						"Type": "SEPA_SUB_BASIN_DISTRICTS",
						"Ref": "Solway",
						"Prime": "P",
						"Overlap": 137.14,
						"Percentage": 100
					}
				]
			},
			"SiteFeature": [
				{
					"Id": "13852",
					"Name": "Vegetated sea cliffs",
					"ActionPlanFeature": "N",
					"WaterFeature": "Y",
					"Category": "Coast",
					"Subcategory": "Supralittoral rock (Coast)",
					"SummaryCondition": "Favourable",
					"LatestAssessedCondition": "Favourable Declining",
					"LatestAssessedVisitDate": "2013-07-30",
					"LatestAssessedSCMcycle": "3",
					"FeatureType": "Habitats",
					"Pressures": {
						"Pressure": [
							{
								"Description": "Dumping/ storage of materials",
								"PressureRecordedAs": "Dumping/spreading/storage of materials"
							},
							{
								"Description": "Invasive species",
								"PressureRecordedAs": "Presence/changing extent invasive species - NATIVE"
							},
							{
								"Description": "Under grazing",
								"PressureRecordedAs": "Grazing - under"
							}
						]
					},
					"HistoryDetails": {
						"Year": [
							{
								"year": "2023",
								"AnnualSummaryCondition": "Favourable"
							},
							{
								"year": "2021",
								"AnnualSummaryCondition": "Favourable"
							},
							{
								"year": "2020",
								"AnnualSummaryCondition": "Favourable"
							},
							{
								"year": "2019",
								"AnnualSummaryCondition": "Favourable"
							},
							{
								"year": "2018",
								"AnnualSummaryCondition": "Favourable"
							},
							{
								"year": "2017",
								"AnnualSummaryCondition": "Favourable"
							},
							{
								"year": "2016",
								"AnnualSummaryCondition": "Favourable"
							},
							{
								"year": "2015",
								"AnnualSummaryCondition": "Favourable"
							},
							{
								"year": "2014",
								"AnnualSummaryCondition": "Favourable"
							},
							{
								"year": "2013",
								"AnnualSummaryCondition": "Favourable"
							},
							{
								"year": "2012",
								"AnnualSummaryCondition": "Favourable"
							},
							{
								"year": "2011",
								"AnnualSummaryCondition": "Favourable"
							},
							{
								"year": "2010",
								"AnnualSummaryCondition": "Favourable"
							}
						]
					}
				}
			]
		}
	]
}