{
	"refreshDateTime": "2024-04-20 15:46:20",
	"Site": [
		{
			"Code": "539",
			"SiteName": "Drummond Lochs",
			"SiteDesignation": "SSSI",
			"LocalAuthority": "Perth and Kinross",
			"SNHArea": "National Operations Central Highland",
			"ProtectedOverlays": {
				"Overlay": [
					{
						"Type": "VICE_COUNTIES",
						"Ref": "Mid Perth",
						"Prime": "P",
						"Overlap": 127.73,
						"Percentage": 100
					},
					{
						"Type": "SEPA_SUB_BASIN_DISTRICTS",
						"Ref": "Tay",
						"Prime": "P",
						"Overlap": 127.73,
						"Percentage": 100
					}
				]
			},
			"SiteFeature": [
				{
					"Id": "10543",
					"Name": "Lowland mixed broadleaved woodland",
					"ActionPlanFeature": "N",
					"WaterFeature": "N",
					"Category": "Woodland",
					"Subcategory": "Broad-leaved, mixed and yew woodland",
					"SummaryCondition": "Favourable",
					"LatestAssessedCondition": "Favourable Maintained",
					"LatestAssessedVisitDate": "2015-09-10",
					"LatestAssessedSCMcycle": "3",
					"FeatureType": "Habitats",
					"Pressures": {
						"Pressure": []
					},
					"HistoryDetails": {
						"Year": [
							{
								"year": "2023",
								"AnnualSummaryCondition": "Favourable"
							},
							{
								"year": "2021",
								"AnnualSummaryCondition": "Favourable"
							},
							{
								"year": "2020",
								"AnnualSummaryCondition": "Favourable"
							},
							{
								"year": "2019",
								"AnnualSummaryCondition": "Favourable"
							},
							{
								"year": "2018",
								"AnnualSummaryCondition": "Favourable"
							},
							{
								"year": "2017",
								"AnnualSummaryCondition": "Favourable"
							},
							{
								"year": "2016",
								"AnnualSummaryCondition": "Favourable"
							},
							{
								"year": "2015",
								"AnnualSummaryCondition": "Favourable"
							},
							{
								"year": "2014",
								"AnnualSummaryCondition": "Favourable"
							},
							{
								"year": "2013",
								"AnnualSummaryCondition": "Favourable"
							},
							{
								"year": "2012",
								"AnnualSummaryCondition": "Favourable"
							},
							{
								"year": "2011",
								"AnnualSummaryCondition": "Favourable"
							},
							{
								"year": "2010",
								"AnnualSummaryCondition": "Favourable"
							}
						]
					}
				},
				{
					"Id": "10544",
					"Name": "Lichen assemblage",
					"ActionPlanFeature": "N",
					"WaterFeature": "N",
					"Category": "Non-vascular plants",
					"Subcategory": "Lichen",
					"SummaryCondition": "Favourable",
					"LatestAssessedCondition": "Favourable Maintained",
					"LatestAssessedVisitDate": "2013-02-08",
					"LatestAssessedSCMcycle": "3",
					"FeatureType": "Species",
					"Pressures": {
						"Pressure": [
							{
								"Description": "Grazing - other",
								"PressureRecordedAs": "Grazing - appropriate level",
								"keywords": "Deer"
							},
							{
								"Description": "Invasive species",
								"PressureRecordedAs": "Presence/changing extent invasive species - NON NATIVE",
								"keywords": "Beech, Rhododendron"
							},
							{
								"Description": "No proactive management",
								"PressureRecordedAs": "Lack of remedial management"
							}
						]
					},
					"HistoryDetails": {
						"Year": [
							{
								"year": "2023",
								"AnnualSummaryCondition": "Favourable"
							},
							{
								"year": "2021",
								"AnnualSummaryCondition": "Favourable"
							},
							{
								"year": "2020",
								"AnnualSummaryCondition": "Favourable"
							},
							{
								"year": "2019",
								"AnnualSummaryCondition": "Favourable"
							},
							{
								"year": "2018",
								"AnnualSummaryCondition": "Favourable"
							},
							{
								"year": "2017",
								"AnnualSummaryCondition": "Favourable"
							},
							{
								"year": "2016",
								"AnnualSummaryCondition": "Favourable"
							},
							{
								"year": "2015",
								"AnnualSummaryCondition": "Favourable"
							},
							{
								"year": "2014",
								"AnnualSummaryCondition": "Favourable"
							},
							{
								"year": "2013",
								"AnnualSummaryCondition": "Favourable"
							},
							{
								"year": "2012",
								"AnnualSummaryCondition": "Favourable"
							},
							{
								"year": "2011",
								"AnnualSummaryCondition": "Favourable"
							},
							{
								"year": "2010",
								"AnnualSummaryCondition": "Recovering"
							}
						]
					}
				},
				{
					"Id": "10545",
					"Name": "Greylag goose (Anser anser), non-breeding",
					"ActionPlanFeature": "N",
					"WaterFeature": "Y",
					"Category": "Birds",
					"Subcategory": "Birds - aggregations of non-breeding birds",
					"SummaryCondition": "Unfavourable",
					"LatestAssessedCondition": "Unfavourable No change",
					"LatestAssessedVisitDate": "2008-03-01",
					"LatestAssessedSCMcycle": "2",
					"FeatureType": "Species",
					"Pressures": {
						"Pressure": []
					},
					"HistoryDetails": {
						"Year": [
							{
								"year": "2023",
								"AnnualSummaryCondition": "Unfavourable"
							},
							{
								"year": "2021",
								"AnnualSummaryCondition": "Unfavourable"
							},
							{
								"year": "2020",
								"AnnualSummaryCondition": "Unfavourable"
							},
							{
								"year": "2019",
								"AnnualSummaryCondition": "Unfavourable"
							},
							{
								"year": "2018",
								"AnnualSummaryCondition": "Unfavourable"
							},
							{
								"year": "2017",
								"AnnualSummaryCondition": "Unfavourable"
							},
							{
								"year": "2016",
								"AnnualSummaryCondition": "Unfavourable"
							},
							{
								"year": "2015",
								"AnnualSummaryCondition": "Unfavourable"
							},
							{
								"year": "2014",
								"AnnualSummaryCondition": "Unfavourable"
							},
							{
								"year": "2013",
								"AnnualSummaryCondition": "Unfavourable"
							},
							{
								"year": "2012",
								"AnnualSummaryCondition": "Unfavourable"
							},
							{
								"year": "2011",
								"AnnualSummaryCondition": "Unfavourable"
							},
							{
								"year": "2010",
								"AnnualSummaryCondition": "Unfavourable"
							}
						]
					}
				}
			]
		}
	]
}